engage_scraper/__init__.py
engage_scraper/scraper_core/__init__.py
engage_scraper/scraper_core/engage_scraper_core.py
engage_scraper/scraper_logics/__init__.py
engage_scraper/scraper_logics/santamonica_scraper_logic.py
engage_scraper/scraper_logics/santamonica_scraper_models.py
engage_scraper/scraper_logics/santamonica_scraper_seeds.py
engage_scraper/scraper_utils/__init__.py
engage_scraper/scraper_utils/dbutils.py
engage_scraper/scraper_utils/elasticsearch.py
engage_scraper/scraper_utils/htmlutils.py
engage_scraper/scraper_utils/textutils.py
engage_scraper/scraper_utils/timeutils.py
engage_scraper/scraper_utils/tweet.py
engage_scraper-0.0.49.dist-info/LICENSE
engage_scraper-0.0.49.dist-info/METADATA
engage_scraper-0.0.49.dist-info/WHEEL
engage_scraper-0.0.49.dist-info/top_level.txt
engage_scraper-0.0.49.dist-info/RECORD
