Metadata-Version: 2.1
Name: engage-scraper
Version: 0.0.49
Summary: An agenda scraper framework for municipalities
Home-page: https://github.com/hackla-engage/engage-scraper
Author: Engage
Author-email: eli.j.selkin@gmail.com
License: UNKNOWN
Platform: UNKNOWN
Classifier: Development Status :: 4 - Beta
Classifier: Programming Language :: Python :: 3
Classifier: License :: OSI Approved :: MIT License
Classifier: Operating System :: OS Independent
License-File: LICENSE
Requires-Dist: soupsieve
Requires-Dist: beautifulsoup4
Requires-Dist: psycopg2-binary
Requires-Dist: pytz
Requires-Dist: requests
Requires-Dist: SQLAlchemy
Requires-Dist: urllib3
Requires-Dist: python-twitter
